<meta>
    <info author="PARADISE" description="MAPPING" version="1.0" type="map" />
<script src="client.lua" type="client" />
    <file src="hotelgarage.txd" />
    <file src="hotelgarage.col" />
    <file src="hotelgarage.dff" />

    <file src="primring.txd" />
    <file src="primring.col" />
    <file src="primring.dff" />

    <file src="hotelfoor.txd" />
    <file src="hotelfoor.col" />
    <file src="hotelfoor.dff" />

    <file src="plitkals.txd" />
    <file src="plitkals.col" />
    <file src="plitkals.dff" />

    <file src="floorls.txd" />
    <file src="floorls.col" />
    <file src="floorls.dff" />

    <file src="neboscreb1.txd" />
    <file src="neboscreb1.col" />
    <file src="neboscreb1.dff" /> 
    <file src="neboscreb2.txd" />
    <file src="neboscreb2.col" />
    <file src="neboscreb2.dff" />
    <file src="neboscreb3.txd" />
    <file src="neboscreb3.col" />
    <file src="neboscreb3.dff" />
    <file src="neboscreb4.txd" />
    <file src="neboscreb4.col" />
    <file src="neboscreb4.dff" />
    <file src="neboscreb5.txd" />
    <file src="neboscreb5.col" />
    <file src="neboscreb5.dff" />

    <file src="scenaopenair1.txd" />
    <file src="scenaopenair1.col" />
    <file src="scenaopenair1.dff" />
    <file src="scenaopenair2.txd" />
    <file src="scenaopenair2.col" />
    <file src="scenaopenair2.dff" />
    <file src="scenaopenair3.txd" />
    <file src="scenaopenair3.col" />
    <file src="scenaopenair3.dff" />
    <file src="scenaopenair4.txd" />
    <file src="scenaopenair4.col" />
    <file src="scenaopenair4.dff" />
    <file src="scenaopenair5.txd" />
    <file src="scenaopenair5.col" />
    <file src="scenaopenair5.dff" />

    <file src="tuningarage1.txd" />
    <file src="tuningarage1.col" />
    <file src="tuningarage1.dff" /> 
    <file src="tuningarage2.txd" />
    <file src="tuningarage2.col" />
    <file src="tuningarage2.dff" />
    <file src="tuningarage3.txd" />
    <file src="tuningarage3.col" />
    <file src="tuningarage3.dff" />

    <file src="stripclub1.txd" />
    <file src="stripclub1.col" />
    <file src="stripclub1.dff" /> 
    <file src="stripclub2.txd" />
    <file src="stripclub2.col" />
    <file src="stripclub2.dff" /> 
    <file src="stripclub3.col" />
    <file src="stripclub3.dff" /> 
    <file src="stripclub4.col" />
    <file src="stripclub4.dff" /> 
    <file src="stripclub5.col" />
    <file src="stripclub5.dff" /> 
    <file src="stripclub6.col" />
    <file src="stripclub6.dff" /> 
    <file src="stripclub7.col" />
    <file src="stripclub7.dff" /> 
    <file src="stripclub8.col" />
    <file src="stripclub8.dff" /> 

    <file src="hdneboscreb.txd" />
    <file src="hdneboscreb.col" />
    <file src="hdneboscreb.dff" /> 

	    <file src="2.txd" />
    <file src="2.col" />
    <file src="2.dff" /> 
	
    <file src="vinewood.txd" />
    <file src="vinewood1.col" />
    <file src="vinewood1.dff" /> 
    <file src="vinewood.col" />
    <file src="vinewood.dff" /> 
	
    <file src="eclipsetower.txd" />
    <file src="eclipsetower.col" />
    <file src="eclipsetower.dff" /> 
    <file src="eclipsetower1.txd" />
    <file src="eclipsetower2.txd" />
    <file src="eclipsetower3.txd" />
    <file src="eclipsetower4.txd" />
    <file src="eclipsetower1.col" />
    <file src="eclipsetower1.dff" />
    <file src="eclipsetower2.col" />
    <file src="eclipsetower2.dff" /> 	
    <file src="eclipsetower3.col" />
    <file src="eclipsetower3.dff" /> 	
</meta>
